pretix_easyverein/__init__.py
pretix_easyverein/apps.py
pretix_easyverein/ev_utils.py
pretix_easyverein/forms.py
pretix_easyverein/models_notyet.py
pretix_easyverein/signals.py
pretix_easyverein/tasks.py
pretix_easyverein/urls.py
pretix_easyverein/views.py
pretix_easyverein/locale/de/LC_MESSAGES/django.mo
pretix_easyverein/locale/de/LC_MESSAGES/django.po
pretix_easyverein/locale/de_Informal/.gitkeep
pretix_easyverein/locale/de_Informal/LC_MESSAGES/django.mo
pretix_easyverein/locale/de_Informal/LC_MESSAGES/django.po
pretix_easyverein/migrations/__init__.py
pretix_easyverein/static/pretix_easyverein/.gitkeep
pretix_easyverein/templates/pretix_easyverein/.gitkeep
pretix_easyverein/templates/pretix_easyverein/organizer_easyverein.html
pretix_easyverein-0.2.0.dist-info/licenses/LICENSE
pretix_easyverein-0.2.0.dist-info/METADATA
pretix_easyverein-0.2.0.dist-info/WHEEL
pretix_easyverein-0.2.0.dist-info/entry_points.txt
pretix_easyverein-0.2.0.dist-info/top_level.txt
pretix_easyverein-0.2.0.dist-info/RECORD
