Metadata-Version: 2.4
Name: pretix-easyverein
Version: 0.2.0
Summary: Connects pretix with easyverein
Author-email: Julian Hammer <julian.hammer@betreiberverein.de>
Maintainer-email: Julian Hammer <julian.hammer@betreiberverein.de>
License-Expression: Apache-2.0
Project-URL: homepage, https://github.com/zam-haus/pretix-easyverein
Project-URL: repository, https://github.com/zam-haus/pretix-easyverein
Keywords: pretix
License-File: LICENSE
Requires-Dist: python-easyverein>=2.1.2
Requires-Dist: requests
Dynamic: license-file
